rose_python_sdk-1.1.1.dist-info/licenses/LICENSE
rose_sdk/__init__.py
rose_sdk/client.py
rose_sdk/exceptions.py
rose_sdk/helpers.py
rose_sdk/models/__init__.py
rose_sdk/models/base.py
rose_sdk/models/batch.py
rose_sdk/models/dataset.py
rose_sdk/models/field.py
rose_sdk/models/permission.py
rose_sdk/models/pipeline.py
rose_sdk/models/query.py
rose_sdk/models/recommendation.py
rose_sdk/models/record.py
rose_sdk/models/role.py
rose_sdk/models/schema.py
rose_sdk/services/__init__.py
rose_sdk/services/account.py
rose_sdk/services/dataset.py
rose_sdk/services/pipeline.py
rose_sdk/services/recommendation.py
rose_sdk/services/role.py
rose_sdk/utils/__init__.py
rose_sdk/utils/account.py
rose_sdk/utils/batch.py
rose_sdk/utils/pipeline.py
rose_sdk/utils/record.py
rose_sdk/utils/schema.py
tests/__init__.py
tests/test_client.py
rose_python_sdk-1.1.1.dist-info/METADATA
rose_python_sdk-1.1.1.dist-info/WHEEL
rose_python_sdk-1.1.1.dist-info/top_level.txt
rose_python_sdk-1.1.1.dist-info/RECORD
